LICENSE
setup.cfg
setup.py
src/wsgi_lib/__init__.py
src/wsgi_lib/request.py
src/wsgi_lib/response.py
src/wsgi_lib/routing.py
src/wsgi_lib.egg-info/PKG-INFO
src/wsgi_lib.egg-info/SOURCES.txt
src/wsgi_lib.egg-info/dependency_links.txt
src/wsgi_lib.egg-info/requires.txt
src/wsgi_lib.egg-info/top_level.txt